shmgr/__init__.py
shmgr/_cli.py
shmgr/py.typed
shmgr-0.1.0.dist-info/METADATA
shmgr-0.1.0.dist-info/WHEEL
shmgr-0.1.0.dist-info/entry_points.txt
shmgr-0.1.0.dist-info/top_level.txt
shmgr-0.1.0.dist-info/RECORD
