Metadata-Version: 2.1
Name: shmgr
Version: 0.1.0
Summary: CLI tool that helps manage shell libraries.
Home-page: https://github.com/bbugyi200/shmgr
Author: Bryan M Bugyi
Author-email: bryanbugyi34@gmail.com
License: MIT license
Platform: UNKNOWN
Classifier: Development Status :: 3 - Alpha
Classifier: Intended Audience :: Developers
Classifier: License :: OSI Approved :: MIT License
Classifier: Natural Language :: English
Classifier: Programming Language :: Python :: 3
Classifier: Programming Language :: Python :: 3.7
Classifier: Programming Language :: Python :: 3.8
Classifier: Programming Language :: Python :: 3.9
Requires-Python: >=3.7
Requires-Dist: pydantic
Requires-Dist: pylogutils
Requires-Dist: python-clap
